googleweather/__init__.py
googleweather/googleweather.py
googleweather-0.0.5.dist-info/LICENSE
googleweather-0.0.5.dist-info/METADATA
googleweather-0.0.5.dist-info/WHEEL
googleweather-0.0.5.dist-info/entry_points.txt
googleweather-0.0.5.dist-info/top_level.txt
googleweather-0.0.5.dist-info/RECORD
